Metadata-Version: 2.1
Name: chae-probability
Version: 1.2
Summary: Gaussian and Binomisl distributions
Home-page: UNKNOWN
Author: Cesar Acuna
Author-email: acuna.cesar.h@gmail.com
License: UNKNOWN
Platform: UNKNOWN
